ademailalias/__init__.py
ademailalias/aliaser.py
ademailalias/cli.py
ademailalias-0.3.0.dist-info/METADATA
ademailalias-0.3.0.dist-info/WHEEL
ademailalias-0.3.0.dist-info/entry_points.txt
ademailalias-0.3.0.dist-info/RECORD
